[
  {
    "id": "27841",
    "data": [
      {
        "name": "р. Рата, 3,5 км, с. Межиріччя, 3,5 км, с. Межиріччя Сокальський район",
        "river": "Вісла",
        "lat": 50.3325,
        "lon": 24.2164,
        "date": "2020-01-21",
        "key": "БСК5..МгО.дм3",
        "value": 3.68,
        "norm": 3,
        "doc": "ОБУВ",
        "mean": 2.96,
        "dev": -0.04,
        "size": 0.9867
      },
      {
        "name": "р. Рата, 3,5 км, с. Межиріччя, 3,5 км, с. Межиріччя Сокальський район",
        "river": "Вісла",
        "lat": 50.3325,
        "lon": 24.2164,
        "date": "2020-02-13",
        "key": "БСК5..МгО.дм3",
        "value": 3.52,
        "norm": 3,
        "doc": "ОБУВ",
        "mean": 2.96,
        "dev": -0.04,
        "size": 0.9867
      },
      {
        "name": "р. Рата, 3,5 км, с. Межиріччя, 3,5 км, с. Межиріччя Сокальський район",
        "river": "Вісла",
        "lat": 50.3325,
        "lon": 24.2164,
        "date": "2020-03-12",
        "key": "БСК5..МгО.дм3",
        "value": 2.06,
        "norm": 3,
        "doc": "ОБУВ",
        "mean": 2.96,
        "dev": -0.04,
        "size": 0.9867
      },
      {
        "name": "р. Рата, 3,5 км, с. Межиріччя, 3,5 км, с. Межиріччя Сокальський район",
        "river": "Вісла",
        "lat": 50.3325,
        "lon": 24.2164,
        "date": "2020-06-11",
        "key": "БСК5..МгО.дм3",
        "value": 2.88,
        "norm": 3,
        "doc": "ОБУВ",
        "mean": 2.96,
        "dev": -0.04,
        "size": 0.9867
      },
      {
        "name": "р. Рата, 3,5 км, с. Межиріччя, 3,5 км, с. Межиріччя Сокальський район",
        "river": "Вісла",
        "lat": 50.3325,
        "lon": 24.2164,
        "date": "2020-04-15",
        "key": "БСК5..МгО.дм3",
        "value": 2.6,
        "norm": 3,
        "doc": "ОБУВ",
        "mean": 2.96,
        "dev": -0.04,
        "size": 0.9867
      },
      {
        "name": "р. Рата, 3,5 км, с. Межиріччя, 3,5 км, с. Межиріччя Сокальський район",
        "river": "Вісла",
        "lat": 50.3325,
        "lon": 24.2164,
        "date": "2020-05-14",
        "key": "БСК5..МгО.дм3",
        "value": 2.58,
        "norm": 3,
        "doc": "ОБУВ",
        "mean": 2.96,
        "dev": -0.04,
        "size": 0.9867
      },
      {
        "name": "р. Рата, 3,5 км, с. Межиріччя, 3,5 км, с. Межиріччя Сокальський район",
        "river": "Вісла",
        "lat": 50.3325,
        "lon": 24.2164,
        "date": "2020-07-08",
        "key": "БСК5..МгО.дм3",
        "value": 4.64,
        "norm": 3,
        "doc": "ОБУВ",
        "mean": 2.96,
        "dev": -0.04,
        "size": 0.9867
      },
      {
        "name": "р. Рата, 3,5 км, с. Межиріччя, 3,5 км, с. Межиріччя Сокальський район",
        "river": "Вісла",
        "lat": 50.3325,
        "lon": 24.2164,
        "date": "2020-09-17",
        "key": "БСК5..МгО.дм3",
        "value": 2.36,
        "norm": 3,
        "doc": "ОБУВ",
        "mean": 2.96,
        "dev": -0.04,
        "size": 0.9867
      },
      {
        "name": "р. Рата, 3,5 км, с. Межиріччя, 3,5 км, с. Межиріччя Сокальський район",
        "river": "Вісла",
        "lat": 50.3325,
        "lon": 24.2164,
        "date": "2020-10-15",
        "key": "БСК5..МгО.дм3",
        "value": 2.32,
        "norm": 3,
        "doc": "ОБУВ",
        "mean": 2.96,
        "dev": -0.04,
        "size": 0.9867
      },
      {
        "name": "р. Рата, 3,5 км, с. Межиріччя, 3,5 км, с. Межиріччя Сокальський район",
        "river": "Вісла",
        "lat": 50.3325,
        "lon": 24.2164,
        "date": "2020-01-21",
        "key": "Кисень.розчинений.МгО2.дм3",
        "value": 8.96,
        "norm": 4,
        "doc": "ОБУВ",
        "mean": 8.7222,
        "dev": 4.7222,
        "size": 2.1806
      },
      {
        "name": "р. Рата, 3,5 км, с. Межиріччя, 3,5 км, с. Межиріччя Сокальський район",
        "river": "Вісла",
        "lat": 50.3325,
        "lon": 24.2164,
        "date": "2020-02-13",
        "key": "Кисень.розчинений.МгО2.дм3",
        "value": 7.2,
        "norm": 4,
        "doc": "ОБУВ",
        "mean": 8.7222,
        "dev": 4.7222,
        "size": 2.1806
      },
      {
        "name": "р. Рата, 3,5 км, с. Межиріччя, 3,5 км, с. Межиріччя Сокальський район",
        "river": "Вісла",
        "lat": 50.3325,
        "lon": 24.2164,
        "date": "2020-03-12",
        "key": "Кисень.розчинений.МгО2.дм3",
        "value": 10.7,
        "norm": 4,
        "doc": "ОБУВ",
        "mean": 8.7222,
        "dev": 4.7222,
        "size": 2.1806
      },
      {
        "name": "р. Рата, 3,5 км, с. Межиріччя, 3,5 км, с. Межиріччя Сокальський район",
        "river": "Вісла",
        "lat": 50.3325,
        "lon": 24.2164,
        "date": "2020-06-11",
        "key": "Кисень.розчинений.МгО2.дм3",
        "value": 8.32,
        "norm": 4,
        "doc": "ОБУВ",
        "mean": 8.7222,
        "dev": 4.7222,
        "size": 2.1806
      },
      {
        "name": "р. Рата, 3,5 км, с. Межиріччя, 3,5 км, с. Межиріччя Сокальський район",
        "river": "Вісла",
        "lat": 50.3325,
        "lon": 24.2164,
        "date": "2020-07-08",
        "key": "Кисень.розчинений.МгО2.дм3",
        "value": 6.84,
        "norm": 4,
        "doc": "ОБУВ",
        "mean": 8.7222,
        "dev": 4.7222,
        "size": 2.1806
      },
      {
        "name": "р. Рата, 3,5 км, с. Межиріччя, 3,5 км, с. Межиріччя Сокальський район",
        "river": "Вісла",
        "lat": 50.3325,
        "lon": 24.2164,
        "date": "2020-08-06",
        "key": "Кисень.розчинений.МгО2.дм3",
        "value": 9.12,
        "norm": 4,
        "doc": "ОБУВ",
        "mean": 8.7222,
        "dev": 4.7222,
        "size": 2.1806
      },
      {
        "name": "р. Рата, 3,5 км, с. Межиріччя, 3,5 км, с. Межиріччя Сокальський район",
        "river": "Вісла",
        "lat": 50.3325,
        "lon": 24.2164,
        "date": "2020-09-17",
        "key": "Кисень.розчинений.МгО2.дм3",
        "value": 8.64,
        "norm": 4,
        "doc": "ОБУВ",
        "mean": 8.7222,
        "dev": 4.7222,
        "size": 2.1806
      },
      {
        "name": "р. Рата, 3,5 км, с. Межиріччя, 3,5 км, с. Межиріччя Сокальський район",
        "river": "Вісла",
        "lat": 50.3325,
        "lon": 24.2164,
        "date": "2020-10-15",
        "key": "Кисень.розчинений.МгО2.дм3",
        "value": 9.28,
        "norm": 4,
        "doc": "ОБУВ",
        "mean": 8.7222,
        "dev": 4.7222,
        "size": 2.1806
      },
      {
        "name": "р. Рата, 3,5 км, с. Межиріччя, 3,5 км, с. Межиріччя Сокальський район",
        "river": "Вісла",
        "lat": 50.3325,
        "lon": 24.2164,
        "date": "2020-11-05",
        "key": "Кисень.розчинений.МгО2.дм3",
        "value": 9.44,
        "norm": 4,
        "doc": "ОБУВ",
        "mean": 8.7222,
        "dev": 4.7222,
        "size": 2.1806
      },
      {
        "name": "р. Рата, 3,5 км, с. Межиріччя, 3,5 км, с. Межиріччя Сокальський район",
        "river": "Вісла",
        "lat": 50.3325,
        "lon": 24.2164,
        "date": "2020-01-21",
        "key": "Сульфат.іони..мг.дм3",
        "value": 22.1,
        "norm": 100,
        "doc": "ОБУВ",
        "mean": 21.521,
        "dev": -78.479,
        "size": 0.2152
      },
      {
        "name": "р. Рата, 3,5 км, с. Межиріччя, 3,5 км, с. Межиріччя Сокальський район",
        "river": "Вісла",
        "lat": 50.3325,
        "lon": 24.2164,
        "date": "2020-02-13",
        "key": "Сульфат.іони..мг.дм3",
        "value": 9.61,
        "norm": 100,
        "doc": "ОБУВ",
        "mean": 21.521,
        "dev": -78.479,
        "size": 0.2152
      },
      {
        "name": "р. Рата, 3,5 км, с. Межиріччя, 3,5 км, с. Межиріччя Сокальський район",
        "river": "Вісла",
        "lat": 50.3325,
        "lon": 24.2164,
        "date": "2020-03-12",
        "key": "Сульфат.іони..мг.дм3",
        "value": 27.9,
        "norm": 100,
        "doc": "ОБУВ",
        "mean": 21.521,
        "dev": -78.479,
        "size": 0.2152
      },
      {
        "name": "р. Рата, 3,5 км, с. Межиріччя, 3,5 км, с. Межиріччя Сокальський район",
        "river": "Вісла",
        "lat": 50.3325,
        "lon": 24.2164,
        "date": "2020-04-15",
        "key": "Сульфат.іони..мг.дм3",
        "value": 22.1,
        "norm": 100,
        "doc": "ОБУВ",
        "mean": 21.521,
        "dev": -78.479,
        "size": 0.2152
      },
      {
        "name": "р. Рата, 3,5 км, с. Межиріччя, 3,5 км, с. Межиріччя Сокальський район",
        "river": "Вісла",
        "lat": 50.3325,
        "lon": 24.2164,
        "date": "2020-05-14",
        "key": "Сульфат.іони..мг.дм3",
        "value": 25.9,
        "norm": 100,
        "doc": "ОБУВ",
        "mean": 21.521,
        "dev": -78.479,
        "size": 0.2152
      },
      {
        "name": "р. Рата, 3,5 км, с. Межиріччя, 3,5 км, с. Межиріччя Сокальський район",
        "river": "Вісла",
        "lat": 50.3325,
        "lon": 24.2164,
        "date": "2020-07-08",
        "key": "Сульфат.іони..мг.дм3",
        "value": 18.3,
        "norm": 100,
        "doc": "ОБУВ",
        "mean": 21.521,
        "dev": -78.479,
        "size": 0.2152
      },
      {
        "name": "р. Рата, 3,5 км, с. Межиріччя, 3,5 км, с. Межиріччя Сокальський район",
        "river": "Вісла",
        "lat": 50.3325,
        "lon": 24.2164,
        "date": "2020-08-06",
        "key": "Сульфат.іони..мг.дм3",
        "value": 23.1,
        "norm": 100,
        "doc": "ОБУВ",
        "mean": 21.521,
        "dev": -78.479,
        "size": 0.2152
      },
      {
        "name": "р. Рата, 3,5 км, с. Межиріччя, 3,5 км, с. Межиріччя Сокальський район",
        "river": "Вісла",
        "lat": 50.3325,
        "lon": 24.2164,
        "date": "2020-09-17",
        "key": "Сульфат.іони..мг.дм3",
        "value": 19.2,
        "norm": 100,
        "doc": "ОБУВ",
        "mean": 21.521,
        "dev": -78.479,
        "size": 0.2152
      },
      {
        "name": "р. Рата, 3,5 км, с. Межиріччя, 3,5 км, с. Межиріччя Сокальський район",
        "river": "Вісла",
        "lat": 50.3325,
        "lon": 24.2164,
        "date": "2020-10-15",
        "key": "Сульфат.іони..мг.дм3",
        "value": 21.1,
        "norm": 100,
        "doc": "ОБУВ",
        "mean": 21.521,
        "dev": -78.479,
        "size": 0.2152
      },
      {
        "name": "р. Рата, 3,5 км, с. Межиріччя, 3,5 км, с. Межиріччя Сокальський район",
        "river": "Вісла",
        "lat": 50.3325,
        "lon": 24.2164,
        "date": "2020-11-05",
        "key": "Сульфат.іони..мг.дм3",
        "value": 25.9,
        "norm": 100,
        "doc": "ОБУВ",
        "mean": 21.521,
        "dev": -78.479,
        "size": 0.2152
      },
      {
        "name": "р. Рата, 3,5 км, с. Межиріччя, 3,5 км, с. Межиріччя Сокальський район",
        "river": "Вісла",
        "lat": 50.3325,
        "lon": 24.2164,
        "date": "2020-01-21",
        "key": "Хлорид.іони..мг.дм3",
        "value": 24.1,
        "norm": 300,
        "doc": "ОБУВ",
        "mean": 25.8182,
        "dev": -274.1818,
        "size": 0.0861
      },
      {
        "name": "р. Рата, 3,5 км, с. Межиріччя, 3,5 км, с. Межиріччя Сокальський район",
        "river": "Вісла",
        "lat": 50.3325,
        "lon": 24.2164,
        "date": "2020-02-13",
        "key": "Хлорид.іони..мг.дм3",
        "value": 35.3,
        "norm": 300,
        "doc": "ОБУВ",
        "mean": 25.8182,
        "dev": -274.1818,
        "size": 0.0861
      },
      {
        "name": "р. Рата, 3,5 км, с. Межиріччя, 3,5 км, с. Межиріччя Сокальський район",
        "river": "Вісла",
        "lat": 50.3325,
        "lon": 24.2164,
        "date": "2020-03-12",
        "key": "Хлорид.іони..мг.дм3",
        "value": 30.9,
        "norm": 300,
        "doc": "ОБУВ",
        "mean": 25.8182,
        "dev": -274.1818,
        "size": 0.0861
      },
      {
        "name": "р. Рата, 3,5 км, с. Межиріччя, 3,5 км, с. Межиріччя Сокальський район",
        "river": "Вісла",
        "lat": 50.3325,
        "lon": 24.2164,
        "date": "2020-06-11",
        "key": "Хлорид.іони..мг.дм3",
        "value": 18.4,
        "norm": 300,
        "doc": "ОБУВ",
        "mean": 25.8182,
        "dev": -274.1818,
        "size": 0.0861
      },
      {
        "name": "р. Рата, 3,5 км, с. Межиріччя, 3,5 км, с. Межиріччя Сокальський район",
        "river": "Вісла",
        "lat": 50.3325,
        "lon": 24.2164,
        "date": "2020-04-15",
        "key": "Хлорид.іони..мг.дм3",
        "value": 33.3,
        "norm": 300,
        "doc": "ОБУВ",
        "mean": 25.8182,
        "dev": -274.1818,
        "size": 0.0861
      },
      {
        "name": "р. Рата, 3,5 км, с. Межиріччя, 3,5 км, с. Межиріччя Сокальський район",
        "river": "Вісла",
        "lat": 50.3325,
        "lon": 24.2164,
        "date": "2020-05-14",
        "key": "Хлорид.іони..мг.дм3",
        "value": 29.2,
        "norm": 300,
        "doc": "ОБУВ",
        "mean": 25.8182,
        "dev": -274.1818,
        "size": 0.0861
      },
      {
        "name": "р. Рата, 3,5 км, с. Межиріччя, 3,5 км, с. Межиріччя Сокальський район",
        "river": "Вісла",
        "lat": 50.3325,
        "lon": 24.2164,
        "date": "2020-07-08",
        "key": "Хлорид.іони..мг.дм3",
        "value": 26.8,
        "norm": 300,
        "doc": "ОБУВ",
        "mean": 25.8182,
        "dev": -274.1818,
        "size": 0.0861
      },
      {
        "name": "р. Рата, 3,5 км, с. Межиріччя, 3,5 км, с. Межиріччя Сокальський район",
        "river": "Вісла",
        "lat": 50.3325,
        "lon": 24.2164,
        "date": "2020-08-06",
        "key": "Хлорид.іони..мг.дм3",
        "value": 29.3,
        "norm": 300,
        "doc": "ОБУВ",
        "mean": 25.8182,
        "dev": -274.1818,
        "size": 0.0861
      },
      {
        "name": "р. Рата, 3,5 км, с. Межиріччя, 3,5 км, с. Межиріччя Сокальський район",
        "river": "Вісла",
        "lat": 50.3325,
        "lon": 24.2164,
        "date": "2020-09-17",
        "key": "Хлорид.іони..мг.дм3",
        "value": 16,
        "norm": 300,
        "doc": "ОБУВ",
        "mean": 25.8182,
        "dev": -274.1818,
        "size": 0.0861
      },
      {
        "name": "р. Рата, 3,5 км, с. Межиріччя, 3,5 км, с. Межиріччя Сокальський район",
        "river": "Вісла",
        "lat": 50.3325,
        "lon": 24.2164,
        "date": "2020-10-15",
        "key": "Хлорид.іони..мг.дм3",
        "value": 17.7,
        "norm": 300,
        "doc": "ОБУВ",
        "mean": 25.8182,
        "dev": -274.1818,
        "size": 0.0861
      },
      {
        "name": "р. Рата, 3,5 км, с. Межиріччя, 3,5 км, с. Межиріччя Сокальський район",
        "river": "Вісла",
        "lat": 50.3325,
        "lon": 24.2164,
        "date": "2020-11-05",
        "key": "Хлорид.іони..мг.дм3",
        "value": 23,
        "norm": 300,
        "doc": "ОБУВ",
        "mean": 25.8182,
        "dev": -274.1818,
        "size": 0.0861
      },
      {
        "name": "р. Рата, 3,5 км, с. Межиріччя, 3,5 км, с. Межиріччя Сокальський район",
        "river": "Вісла",
        "lat": 50.3325,
        "lon": 24.2164,
        "date": "2020-01-21",
        "key": "Амоній.іони..мг.дм3",
        "value": 2.08,
        "norm": 0.5,
        "doc": "ОБУВ",
        "mean": 0.847,
        "dev": 0.347,
        "size": 1.694
      },
      {
        "name": "р. Рата, 3,5 км, с. Межиріччя, 3,5 км, с. Межиріччя Сокальський район",
        "river": "Вісла",
        "lat": 50.3325,
        "lon": 24.2164,
        "date": "2020-02-13",
        "key": "Амоній.іони..мг.дм3",
        "value": 0.99,
        "norm": 0.5,
        "doc": "ОБУВ",
        "mean": 0.847,
        "dev": 0.347,
        "size": 1.694
      },
      {
        "name": "р. Рата, 3,5 км, с. Межиріччя, 3,5 км, с. Межиріччя Сокальський район",
        "river": "Вісла",
        "lat": 50.3325,
        "lon": 24.2164,
        "date": "2020-03-12",
        "key": "Амоній.іони..мг.дм3",
        "value": 0.81,
        "norm": 0.5,
        "doc": "ОБУВ",
        "mean": 0.847,
        "dev": 0.347,
        "size": 1.694
      },
      {
        "name": "р. Рата, 3,5 км, с. Межиріччя, 3,5 км, с. Межиріччя Сокальський район",
        "river": "Вісла",
        "lat": 50.3325,
        "lon": 24.2164,
        "date": "2020-06-11",
        "key": "Амоній.іони..мг.дм3",
        "value": 1.66,
        "norm": 0.5,
        "doc": "ОБУВ",
        "mean": 0.847,
        "dev": 0.347,
        "size": 1.694
      },
      {
        "name": "р. Рата, 3,5 км, с. Межиріччя, 3,5 км, с. Межиріччя Сокальський район",
        "river": "Вісла",
        "lat": 50.3325,
        "lon": 24.2164,
        "date": "2020-04-15",
        "key": "Амоній.іони..мг.дм3",
        "value": 0.52,
        "norm": 0.5,
        "doc": "ОБУВ",
        "mean": 0.847,
        "dev": 0.347,
        "size": 1.694
      },
      {
        "name": "р. Рата, 3,5 км, с. Межиріччя, 3,5 км, с. Межиріччя Сокальський район",
        "river": "Вісла",
        "lat": 50.3325,
        "lon": 24.2164,
        "date": "2020-05-14",
        "key": "Амоній.іони..мг.дм3",
        "value": 0.66,
        "norm": 0.5,
        "doc": "ОБУВ",
        "mean": 0.847,
        "dev": 0.347,
        "size": 1.694
      },
      {
        "name": "р. Рата, 3,5 км, с. Межиріччя, 3,5 км, с. Межиріччя Сокальський район",
        "river": "Вісла",
        "lat": 50.3325,
        "lon": 24.2164,
        "date": "2020-08-06",
        "key": "Амоній.іони..мг.дм3",
        "value": 0.32,
        "norm": 0.5,
        "doc": "ОБУВ",
        "mean": 0.847,
        "dev": 0.347,
        "size": 1.694
      },
      {
        "name": "р. Рата, 3,5 км, с. Межиріччя, 3,5 км, с. Межиріччя Сокальський район",
        "river": "Вісла",
        "lat": 50.3325,
        "lon": 24.2164,
        "date": "2020-09-17",
        "key": "Амоній.іони..мг.дм3",
        "value": 0.48,
        "norm": 0.5,
        "doc": "ОБУВ",
        "mean": 0.847,
        "dev": 0.347,
        "size": 1.694
      },
      {
        "name": "р. Рата, 3,5 км, с. Межиріччя, 3,5 км, с. Межиріччя Сокальський район",
        "river": "Вісла",
        "lat": 50.3325,
        "lon": 24.2164,
        "date": "2020-10-15",
        "key": "Амоній.іони..мг.дм3",
        "value": 0.52,
        "norm": 0.5,
        "doc": "ОБУВ",
        "mean": 0.847,
        "dev": 0.347,
        "size": 1.694
      },
      {
        "name": "р. Рата, 3,5 км, с. Межиріччя, 3,5 км, с. Межиріччя Сокальський район",
        "river": "Вісла",
        "lat": 50.3325,
        "lon": 24.2164,
        "date": "2020-11-05",
        "key": "Амоній.іони..мг.дм3",
        "value": 0.43,
        "norm": 0.5,
        "doc": "ОБУВ",
        "mean": 0.847,
        "dev": 0.347,
        "size": 1.694
      },
      {
        "name": "р. Рата, 3,5 км, с. Межиріччя, 3,5 км, с. Межиріччя Сокальський район",
        "river": "Вісла",
        "lat": 50.3325,
        "lon": 24.2164,
        "date": "2020-01-21",
        "key": "Нітрат.іони..мг.дм3",
        "value": 0.57,
        "norm": 40,
        "doc": "ОБУВ",
        "mean": 0.7,
        "dev": -39.3,
        "size": 0.0175
      },
      {
        "name": "р. Рата, 3,5 км, с. Межиріччя, 3,5 км, с. Межиріччя Сокальський район",
        "river": "Вісла",
        "lat": 50.3325,
        "lon": 24.2164,
        "date": "2020-02-13",
        "key": "Нітрат.іони..мг.дм3",
        "value": 0.78,
        "norm": 40,
        "doc": "ОБУВ",
        "mean": 0.7,
        "dev": -39.3,
        "size": 0.0175
      },
      {
        "name": "р. Рата, 3,5 км, с. Межиріччя, 3,5 км, с. Межиріччя Сокальський район",
        "river": "Вісла",
        "lat": 50.3325,
        "lon": 24.2164,
        "date": "2020-03-12",
        "key": "Нітрат.іони..мг.дм3",
        "value": 0.74,
        "norm": 40,
        "doc": "ОБУВ",
        "mean": 0.7,
        "dev": -39.3,
        "size": 0.0175
      },
      {
        "name": "р. Рата, 3,5 км, с. Межиріччя, 3,5 км, с. Межиріччя Сокальський район",
        "river": "Вісла",
        "lat": 50.3325,
        "lon": 24.2164,
        "date": "2020-06-11",
        "key": "Нітрат.іони..мг.дм3",
        "value": 0.57,
        "norm": 40,
        "doc": "ОБУВ",
        "mean": 0.7,
        "dev": -39.3,
        "size": 0.0175
      },
      {
        "name": "р. Рата, 3,5 км, с. Межиріччя, 3,5 км, с. Межиріччя Сокальський район",
        "river": "Вісла",
        "lat": 50.3325,
        "lon": 24.2164,
        "date": "2020-04-15",
        "key": "Нітрат.іони..мг.дм3",
        "value": 0.04,
        "norm": 40,
        "doc": "ОБУВ",
        "mean": 0.7,
        "dev": -39.3,
        "size": 0.0175
      },
      {
        "name": "р. Рата, 3,5 км, с. Межиріччя, 3,5 км, с. Межиріччя Сокальський район",
        "river": "Вісла",
        "lat": 50.3325,
        "lon": 24.2164,
        "date": "2020-05-14",
        "key": "Нітрат.іони..мг.дм3",
        "value": 0.04,
        "norm": 40,
        "doc": "ОБУВ",
        "mean": 0.7,
        "dev": -39.3,
        "size": 0.0175
      },
      {
        "name": "р. Рата, 3,5 км, с. Межиріччя, 3,5 км, с. Межиріччя Сокальський район",
        "river": "Вісла",
        "lat": 50.3325,
        "lon": 24.2164,
        "date": "2020-07-08",
        "key": "Нітрат.іони..мг.дм3",
        "value": 0.35,
        "norm": 40,
        "doc": "ОБУВ",
        "mean": 0.7,
        "dev": -39.3,
        "size": 0.0175
      },
      {
        "name": "р. Рата, 3,5 км, с. Межиріччя, 3,5 км, с. Межиріччя Сокальський район",
        "river": "Вісла",
        "lat": 50.3325,
        "lon": 24.2164,
        "date": "2020-08-06",
        "key": "Нітрат.іони..мг.дм3",
        "value": 0.48,
        "norm": 40,
        "doc": "ОБУВ",
        "mean": 0.7,
        "dev": -39.3,
        "size": 0.0175
      },
      {
        "name": "р. Рата, 3,5 км, с. Межиріччя, 3,5 км, с. Межиріччя Сокальський район",
        "river": "Вісла",
        "lat": 50.3325,
        "lon": 24.2164,
        "date": "2020-09-17",
        "key": "Нітрат.іони..мг.дм3",
        "value": 0.43,
        "norm": 40,
        "doc": "ОБУВ",
        "mean": 0.7,
        "dev": -39.3,
        "size": 0.0175
      },
      {
        "name": "р. Рата, 3,5 км, с. Межиріччя, 3,5 км, с. Межиріччя Сокальський район",
        "river": "Вісла",
        "lat": 50.3325,
        "lon": 24.2164,
        "date": "2020-10-15",
        "key": "Нітрат.іони..мг.дм3",
        "value": 1.09,
        "norm": 40,
        "doc": "ОБУВ",
        "mean": 0.7,
        "dev": -39.3,
        "size": 0.0175
      },
      {
        "name": "р. Рата, 3,5 км, с. Межиріччя, 3,5 км, с. Межиріччя Сокальський район",
        "river": "Вісла",
        "lat": 50.3325,
        "lon": 24.2164,
        "date": "2020-11-05",
        "key": "Нітрат.іони..мг.дм3",
        "value": 2.61,
        "norm": 40,
        "doc": "ОБУВ",
        "mean": 0.7,
        "dev": -39.3,
        "size": 0.0175
      },
      {
        "name": "р. Рата, 3,5 км, с. Межиріччя, 3,5 км, с. Межиріччя Сокальський район",
        "river": "Вісла",
        "lat": 50.3325,
        "lon": 24.2164,
        "date": "2020-01-21",
        "key": "Нітрит.іони..мг.дм3",
        "value": 0.06,
        "norm": 0.08,
        "doc": "ОБУВ",
        "mean": 0.1073,
        "dev": 0.0273,
        "size": 1.3409
      },
      {
        "name": "р. Рата, 3,5 км, с. Межиріччя, 3,5 км, с. Межиріччя Сокальський район",
        "river": "Вісла",
        "lat": 50.3325,
        "lon": 24.2164,
        "date": "2020-02-13",
        "key": "Нітрит.іони..мг.дм3",
        "value": 0.1,
        "norm": 0.08,
        "doc": "ОБУВ",
        "mean": 0.1073,
        "dev": 0.0273,
        "size": 1.3409
      },
      {
        "name": "р. Рата, 3,5 км, с. Межиріччя, 3,5 км, с. Межиріччя Сокальський район",
        "river": "Вісла",
        "lat": 50.3325,
        "lon": 24.2164,
        "date": "2020-03-12",
        "key": "Нітрит.іони..мг.дм3",
        "value": 0.09,
        "norm": 0.08,
        "doc": "ОБУВ",
        "mean": 0.1073,
        "dev": 0.0273,
        "size": 1.3409
      },
      {
        "name": "р. Рата, 3,5 км, с. Межиріччя, 3,5 км, с. Межиріччя Сокальський район",
        "river": "Вісла",
        "lat": 50.3325,
        "lon": 24.2164,
        "date": "2020-06-11",
        "key": "Нітрит.іони..мг.дм3",
        "value": 0.05,
        "norm": 0.08,
        "doc": "ОБУВ",
        "mean": 0.1073,
        "dev": 0.0273,
        "size": 1.3409
      },
      {
        "name": "р. Рата, 3,5 км, с. Межиріччя, 3,5 км, с. Межиріччя Сокальський район",
        "river": "Вісла",
        "lat": 50.3325,
        "lon": 24.2164,
        "date": "2020-04-15",
        "key": "Нітрит.іони..мг.дм3",
        "value": 0.09,
        "norm": 0.08,
        "doc": "ОБУВ",
        "mean": 0.1073,
        "dev": 0.0273,
        "size": 1.3409
      },
      {
        "name": "р. Рата, 3,5 км, с. Межиріччя, 3,5 км, с. Межиріччя Сокальський район",
        "river": "Вісла",
        "lat": 50.3325,
        "lon": 24.2164,
        "date": "2020-05-14",
        "key": "Нітрит.іони..мг.дм3",
        "value": 0.14,
        "norm": 0.08,
        "doc": "ОБУВ",
        "mean": 0.1073,
        "dev": 0.0273,
        "size": 1.3409
      },
      {
        "name": "р. Рата, 3,5 км, с. Межиріччя, 3,5 км, с. Межиріччя Сокальський район",
        "river": "Вісла",
        "lat": 50.3325,
        "lon": 24.2164,
        "date": "2020-07-08",
        "key": "Нітрит.іони..мг.дм3",
        "value": 0.16,
        "norm": 0.08,
        "doc": "ОБУВ",
        "mean": 0.1073,
        "dev": 0.0273,
        "size": 1.3409
      },
      {
        "name": "р. Рата, 3,5 км, с. Межиріччя, 3,5 км, с. Межиріччя Сокальський район",
        "river": "Вісла",
        "lat": 50.3325,
        "lon": 24.2164,
        "date": "2020-08-06",
        "key": "Нітрит.іони..мг.дм3",
        "value": 0.1,
        "norm": 0.08,
        "doc": "ОБУВ",
        "mean": 0.1073,
        "dev": 0.0273,
        "size": 1.3409
      },
      {
        "name": "р. Рата, 3,5 км, с. Межиріччя, 3,5 км, с. Межиріччя Сокальський район",
        "river": "Вісла",
        "lat": 50.3325,
        "lon": 24.2164,
        "date": "2020-09-17",
        "key": "Нітрит.іони..мг.дм3",
        "value": 0.11,
        "norm": 0.08,
        "doc": "ОБУВ",
        "mean": 0.1073,
        "dev": 0.0273,
        "size": 1.3409
      },
      {
        "name": "р. Рата, 3,5 км, с. Межиріччя, 3,5 км, с. Межиріччя Сокальський район",
        "river": "Вісла",
        "lat": 50.3325,
        "lon": 24.2164,
        "date": "2020-10-15",
        "key": "Нітрит.іони..мг.дм3",
        "value": 0.14,
        "norm": 0.08,
        "doc": "ОБУВ",
        "mean": 0.1073,
        "dev": 0.0273,
        "size": 1.3409
      },
      {
        "name": "р. Рата, 3,5 км, с. Межиріччя, 3,5 км, с. Межиріччя Сокальський район",
        "river": "Вісла",
        "lat": 50.3325,
        "lon": 24.2164,
        "date": "2020-11-05",
        "key": "Нітрит.іони..мг.дм3",
        "value": 0.14,
        "norm": 0.08,
        "doc": "ОБУВ",
        "mean": 0.1073,
        "dev": 0.0273,
        "size": 1.3409
      },
      {
        "name": "р. Рата, 3,5 км, с. Межиріччя, 3,5 км, с. Межиріччя Сокальський район",
        "river": "Вісла",
        "lat": 50.3325,
        "lon": 24.2164,
        "date": "2020-01-21",
        "key": "Фосфат.іони..поліфосфати...мг.дм3",
        "value": 0.32,
        "norm": null,
        "doc": null,
        "mean": 0.23,
        "dev": null,
        "size": null
      },
      {
        "name": "р. Рата, 3,5 км, с. Межиріччя, 3,5 км, с. Межиріччя Сокальський район",
        "river": "Вісла",
        "lat": 50.3325,
        "lon": 24.2164,
        "date": "2020-02-13",
        "key": "Фосфат.іони..поліфосфати...мг.дм3",
        "value": 0.17,
        "norm": null,
        "doc": null,
        "mean": 0.23,
        "dev": null,
        "size": null
      },
      {
        "name": "р. Рата, 3,5 км, с. Межиріччя, 3,5 км, с. Межиріччя Сокальський район",
        "river": "Вісла",
        "lat": 50.3325,
        "lon": 24.2164,
        "date": "2020-03-12",
        "key": "Фосфат.іони..поліфосфати...мг.дм3",
        "value": 0.19,
        "norm": null,
        "doc": null,
        "mean": 0.23,
        "dev": null,
        "size": null
      },
      {
        "name": "р. Рата, 3,5 км, с. Межиріччя, 3,5 км, с. Межиріччя Сокальський район",
        "river": "Вісла",
        "lat": 50.3325,
        "lon": 24.2164,
        "date": "2020-06-11",
        "key": "Фосфат.іони..поліфосфати...мг.дм3",
        "value": 0.17,
        "norm": null,
        "doc": null,
        "mean": 0.23,
        "dev": null,
        "size": null
      },
      {
        "name": "р. Рата, 3,5 км, с. Межиріччя, 3,5 км, с. Межиріччя Сокальський район",
        "river": "Вісла",
        "lat": 50.3325,
        "lon": 24.2164,
        "date": "2020-04-15",
        "key": "Фосфат.іони..поліфосфати...мг.дм3",
        "value": 0.15,
        "norm": null,
        "doc": null,
        "mean": 0.23,
        "dev": null,
        "size": null
      },
      {
        "name": "р. Рата, 3,5 км, с. Межиріччя, 3,5 км, с. Межиріччя Сокальський район",
        "river": "Вісла",
        "lat": 50.3325,
        "lon": 24.2164,
        "date": "2020-05-14",
        "key": "Фосфат.іони..поліфосфати...мг.дм3",
        "value": 0.26,
        "norm": null,
        "doc": null,
        "mean": 0.23,
        "dev": null,
        "size": null
      },
      {
        "name": "р. Рата, 3,5 км, с. Межиріччя, 3,5 км, с. Межиріччя Сокальський район",
        "river": "Вісла",
        "lat": 50.3325,
        "lon": 24.2164,
        "date": "2020-07-08",
        "key": "Фосфат.іони..поліфосфати...мг.дм3",
        "value": 0.27,
        "norm": null,
        "doc": null,
        "mean": 0.23,
        "dev": null,
        "size": null
      },
      {
        "name": "р. Рата, 3,5 км, с. Межиріччя, 3,5 км, с. Межиріччя Сокальський район",
        "river": "Вісла",
        "lat": 50.3325,
        "lon": 24.2164,
        "date": "2020-08-06",
        "key": "Фосфат.іони..поліфосфати...мг.дм3",
        "value": 0.16,
        "norm": null,
        "doc": null,
        "mean": 0.23,
        "dev": null,
        "size": null
      },
      {
        "name": "р. Рата, 3,5 км, с. Межиріччя, 3,5 км, с. Межиріччя Сокальський район",
        "river": "Вісла",
        "lat": 50.3325,
        "lon": 24.2164,
        "date": "2020-09-17",
        "key": "Фосфат.іони..поліфосфати...мг.дм3",
        "value": 0.27,
        "norm": null,
        "doc": null,
        "mean": 0.23,
        "dev": null,
        "size": null
      },
      {
        "name": "р. Рата, 3,5 км, с. Межиріччя, 3,5 км, с. Межиріччя Сокальський район",
        "river": "Вісла",
        "lat": 50.3325,
        "lon": 24.2164,
        "date": "2020-10-15",
        "key": "Фосфат.іони..поліфосфати...мг.дм3",
        "value": 0.19,
        "norm": null,
        "doc": null,
        "mean": 0.23,
        "dev": null,
        "size": null
      },
      {
        "name": "р. Рата, 3,5 км, с. Межиріччя, 3,5 км, с. Межиріччя Сокальський район",
        "river": "Вісла",
        "lat": 50.3325,
        "lon": 24.2164,
        "date": "2020-11-05",
        "key": "Фосфат.іони..поліфосфати...мг.дм3",
        "value": 0.38,
        "norm": null,
        "doc": null,
        "mean": 0.23,
        "dev": null,
        "size": null
      },
      {
        "name": "р. Рата, 3,5 км, с. Межиріччя, 3,5 км, с. Межиріччя Сокальський район",
        "river": "Вісла",
        "lat": 50.3325,
        "lon": 24.2164,
        "date": "2020-01-21",
        "key": "Хімічне.споживання.кисню..мгО.дм3",
        "value": 28,
        "norm": 9,
        "doc": "ДСТУ",
        "mean": 32.1091,
        "dev": 23.1091,
        "size": 3.5677
      },
      {
        "name": "р. Рата, 3,5 км, с. Межиріччя, 3,5 км, с. Межиріччя Сокальський район",
        "river": "Вісла",
        "lat": 50.3325,
        "lon": 24.2164,
        "date": "2020-02-13",
        "key": "Хімічне.споживання.кисню..мгО.дм3",
        "value": 26.1,
        "norm": 9,
        "doc": "ДСТУ",
        "mean": 32.1091,
        "dev": 23.1091,
        "size": 3.5677
      },
      {
        "name": "р. Рата, 3,5 км, с. Межиріччя, 3,5 км, с. Межиріччя Сокальський район",
        "river": "Вісла",
        "lat": 50.3325,
        "lon": 24.2164,
        "date": "2020-03-12",
        "key": "Хімічне.споживання.кисню..мгО.дм3",
        "value": 27,
        "norm": 9,
        "doc": "ДСТУ",
        "mean": 32.1091,
        "dev": 23.1091,
        "size": 3.5677
      },
      {
        "name": "р. Рата, 3,5 км, с. Межиріччя, 3,5 км, с. Межиріччя Сокальський район",
        "river": "Вісла",
        "lat": 50.3325,
        "lon": 24.2164,
        "date": "2020-06-11",
        "key": "Хімічне.споживання.кисню..мгО.дм3",
        "value": 45,
        "norm": 9,
        "doc": "ДСТУ",
        "mean": 32.1091,
        "dev": 23.1091,
        "size": 3.5677
      },
      {
        "name": "р. Рата, 3,5 км, с. Межиріччя, 3,5 км, с. Межиріччя Сокальський район",
        "river": "Вісла",
        "lat": 50.3325,
        "lon": 24.2164,
        "date": "2020-04-15",
        "key": "Хімічне.споживання.кисню..мгО.дм3",
        "value": 23,
        "norm": 9,
        "doc": "ДСТУ",
        "mean": 32.1091,
        "dev": 23.1091,
        "size": 3.5677
      },
      {
        "name": "р. Рата, 3,5 км, с. Межиріччя, 3,5 км, с. Межиріччя Сокальський район",
        "river": "Вісла",
        "lat": 50.3325,
        "lon": 24.2164,
        "date": "2020-05-14",
        "key": "Хімічне.споживання.кисню..мгО.дм3",
        "value": 42.1,
        "norm": 9,
        "doc": "ДСТУ",
        "mean": 32.1091,
        "dev": 23.1091,
        "size": 3.5677
      },
      {
        "name": "р. Рата, 3,5 км, с. Межиріччя, 3,5 км, с. Межиріччя Сокальський район",
        "river": "Вісла",
        "lat": 50.3325,
        "lon": 24.2164,
        "date": "2020-07-08",
        "key": "Хімічне.споживання.кисню..мгО.дм3",
        "value": 37,
        "norm": 9,
        "doc": "ДСТУ",
        "mean": 32.1091,
        "dev": 23.1091,
        "size": 3.5677
      },
      {
        "name": "р. Рата, 3,5 км, с. Межиріччя, 3,5 км, с. Межиріччя Сокальський район",
        "river": "Вісла",
        "lat": 50.3325,
        "lon": 24.2164,
        "date": "2020-08-06",
        "key": "Хімічне.споживання.кисню..мгО.дм3",
        "value": 42,
        "norm": 9,
        "doc": "ДСТУ",
        "mean": 32.1091,
        "dev": 23.1091,
        "size": 3.5677
      },
      {
        "name": "р. Рата, 3,5 км, с. Межиріччя, 3,5 км, с. Межиріччя Сокальський район",
        "river": "Вісла",
        "lat": 50.3325,
        "lon": 24.2164,
        "date": "2020-09-17",
        "key": "Хімічне.споживання.кисню..мгО.дм3",
        "value": 24,
        "norm": 9,
        "doc": "ДСТУ",
        "mean": 32.1091,
        "dev": 23.1091,
        "size": 3.5677
      },
      {
        "name": "р. Рата, 3,5 км, с. Межиріччя, 3,5 км, с. Межиріччя Сокальський район",
        "river": "Вісла",
        "lat": 50.3325,
        "lon": 24.2164,
        "date": "2020-10-15",
        "key": "Хімічне.споживання.кисню..мгО.дм3",
        "value": 28,
        "norm": 9,
        "doc": "ДСТУ",
        "mean": 32.1091,
        "dev": 23.1091,
        "size": 3.5677
      },
      {
        "name": "р. Рата, 3,5 км, с. Межиріччя, 3,5 км, с. Межиріччя Сокальський район",
        "river": "Вісла",
        "lat": 50.3325,
        "lon": 24.2164,
        "date": "2020-11-05",
        "key": "Хімічне.споживання.кисню..мгО.дм3",
        "value": 31,
        "norm": 9,
        "doc": "ДСТУ",
        "mean": 32.1091,
        "dev": 23.1091,
        "size": 3.5677
      }
    ]
  }
]
